psscriptanalyzer_hook.py
docs/conf.py
psscriptanalyzer_pre_commit-1.0.0.dist-info/METADATA
psscriptanalyzer_pre_commit-1.0.0.dist-info/WHEEL
psscriptanalyzer_pre_commit-1.0.0.dist-info/entry_points.txt
psscriptanalyzer_pre_commit-1.0.0.dist-info/licenses/LICENSE
psscriptanalyzer_pre_commit-1.0.0.dist-info/RECORD
