Metadata-Version: 2.1
Name: psscriptanalyzer-pre-commit
Version: 1.0.0
Summary: Pre-commit hook for PSScriptAnalyzer - PowerShell static analysis and formatting
Project-URL: Homepage, https://github.com/thetestlabs/psscriptanalyzer-pre-commit
Project-URL: Repository, https://github.com/thetestlabs/psscriptanalyzer-pre-commit
Project-URL: Issues, https://github.com/thetestlabs/psscriptanalyzer-pre-commit/issues
Project-URL: Documentation, https://psscriptanalyzer-pre-commit.readthedocs.io/
Project-URL: Changelog, https://github.com/thetestlabs/psscriptanalyzer-pre-commit/blob/main/CHANGELOG.md
Author-email: Chris McQuaid <chris@thetestlabs.io>
Maintainer-email: Chris McQuaid <chris@thetestlabs.io>
License: MIT
License-File: LICENSE
Keywords: code-quality,formatting,linting,powershell,pre-commit,psscriptanalyzer,static-analysis
Classifier: Development Status :: 5 - Production/Stable
Classifier: Environment :: Console
Classifier: Intended Audience :: Developers
Classifier: License :: OSI Approved :: MIT License
Classifier: Operating System :: OS Independent
Classifier: Programming Language :: Other
Classifier: Programming Language :: Python :: 3
Classifier: Programming Language :: Python :: 3.9
Classifier: Programming Language :: Python :: 3.10
Classifier: Programming Language :: Python :: 3.11
Classifier: Programming Language :: Python :: 3.12
Classifier: Programming Language :: Python :: 3.13
Classifier: Topic :: Software Development :: Quality Assurance
Classifier: Topic :: Software Development :: Testing
Classifier: Topic :: Text Processing :: Linguistic
Classifier: Typing :: Typed
Requires-Python: >=3.9
